more_systemctl_status-0.1.0.dist-info/DESCRIPTION.rst
more_systemctl_status-0.1.0.dist-info/METADATA
more_systemctl_status-0.1.0.dist-info/RECORD
more_systemctl_status-0.1.0.dist-info/WHEEL
more_systemctl_status-0.1.0.dist-info/entry_points.txt
more_systemctl_status-0.1.0.dist-info/metadata.json
more_systemctl_status-0.1.0.dist-info/top_level.txt
moresystemctlstatus/__init__.py
moresystemctlstatus/moresystemctlstatus.py
